[
  {"maker": "A. Lange & Söhne", "caliber": "L951.1", "bph": 18000, "lift_angle": 54.0},
  {"maker": "A. Lange & Söhne", "caliber": "L121.1", "bph": 21600, "lift_angle": 53.0},
  {"maker": "Citizen", "caliber": "0820", "bph": 28800, "lift_angle": 51.0},
  {"maker": "Citizen", "caliber": "8203 (Miyota)", "bph": 21600, "lift_angle": 53.0},
  {"maker": "ETA", "caliber": "2801-2", "bph": 28800, "lift_angle": 50.0},
  {"maker": "ETA", "caliber": "2804-2", "bph": 28800, "lift_angle": 50.0},
  {"maker": "ETA", "caliber": "2824-2", "bph": 28800, "lift_angle": 50.0},
  {"maker": "ETA", "caliber": "2836-2", "bph": 28800, "lift_angle": 50.0},
  {"maker": "ETA", "caliber": "2892-A2", "bph": 28800, "lift_angle": 51.0},
  {"maker": "ETA", "caliber": "6497 (Unitas)", "bph": 18000, "lift_angle": 53.0},
  {"maker": "ETA", "caliber": "6498 (Unitas)", "bph": 18000, "lift_angle": 53.0},
  {"maker": "ETA", "caliber": "7001 (Peseux)", "bph": 21600, "lift_angle": 52.0},
  {"maker": "ETA", "caliber": "7750 Valjoux", "bph": 28800, "lift_angle": 50.0},
  {"maker": "ETA", "caliber": "955.112 (quartz)", "bph": 32768, "lift_angle": 0.0},
  {"maker": "Generic", "caliber": "Hi-Beat 36000", "bph": 36000, "lift_angle": 52.0},
  {"maker": "Hamilton", "caliber": "H-10 (ETA C07.111)", "bph": 21600, "lift_angle": 50.0},
  {"maker": "Jaeger-LeCoultre", "caliber": "899", "bph": 28800, "lift_angle": 52.0},
  {"maker": "Jaeger-LeCoultre", "caliber": "920", "bph": 28800, "lift_angle": 52.0},
  {"maker": "Miyota", "caliber": "8215", "bph": 21600, "lift_angle": 53.0},
  {"maker": "Miyota", "caliber": "82S0", "bph": 21600, "lift_angle": 53.0},
  {"maker": "Miyota", "caliber": "9015", "bph": 28800, "lift_angle": 51.0},
  {"maker": "Miyota", "caliber": "9039", "bph": 28800, "lift_angle": 51.0},
  {"maker": "Omega", "caliber": "1120", "bph": 28800, "lift_angle": 51.0},
  {"maker": "Omega", "caliber": "1861", "bph": 21600, "lift_angle": 50.0},
  {"maker": "Omega", "caliber": "8500 Co-Axial", "bph": 25200, "lift_angle": 38.0},
  {"maker": "Omega", "caliber": "8800 Co-Axial", "bph": 25200, "lift_angle": 38.0},
  {"maker": "Orient", "caliber": "F6922", "bph": 21600, "lift_angle": 52.0},
  {"maker": "Patek Philippe", "caliber": "324 S C", "bph": 28800, "lift_angle": 52.0},
  {"maker": "Patek Philippe", "caliber": "215 PS", "bph": 28800, "lift_angle": 52.0},
  {"maker": "Rolex", "caliber": "3135", "bph": 28800, "lift_angle": 52.0},
  {"maker": "Rolex", "caliber": "3186", "bph": 28800, "lift_angle": 52.0},
  {"maker": "Rolex", "caliber": "3235", "bph": 28800, "lift_angle": 52.0},
  {"maker": "Rolex", "caliber": "2236", "bph": 28800, "lift_angle": 52.0},
  {"maker": "Seagull", "caliber": "ST1612 (Unitas clone)", "bph": 21600, "lift_angle": 50.0},
  {"maker": "Seiko", "caliber": "7S26", "bph": 21600, "lift_angle": 52.0},
  {"maker": "Seiko", "caliber": "4R36", "bph": 21600, "lift_angle": 52.0},
  {"maker": "Seiko", "caliber": "6R15", "bph": 21600, "lift_angle": 53.0},
  {"maker": "Seiko", "caliber": "6R35", "bph": 21600, "lift_angle": 53.0},
  {"maker": "Seiko", "caliber": "6309", "bph": 21600, "lift_angle": 52.0},
  {"maker": "Seiko", "caliber": "NH35 (Seiko/TMI)", "bph": 21600, "lift_angle": 53.0},
  {"maker": "Sellita", "caliber": "SW200-1", "bph": 28800, "lift_angle": 50.0},
  {"maker": "Sellita", "caliber": "SW300-1", "bph": 28800, "lift_angle": 51.0},
  {"maker": "Sellita", "caliber": "SW500", "bph": 28800, "lift_angle": 50.0},
  {"maker": "Tudor", "caliber": "MT5612", "bph": 28800, "lift_angle": 52.0},
  {"maker": "Vacheron Constantin", "caliber": "2450", "bph": 28800, "lift_angle": 52.0},
  {"maker": "Zenith", "caliber": "El Primero 400", "bph": 36000, "lift_angle": 49.0}
]
